{
	"geode": "5.2.0",
	"gd": {
		"win": "2.2081",
		"android": "2.2081",
		"mac": "2.2081",
		"ios": "2.2081"
	},
	"id": "glowrock.delicious-decimals",
	"name": "Delicious Decimals",
	"version": "v1.0.0",
	"developer": "GlowRock",
	"description": "Add as many decimals as your hunger desires!",
	"tags": ["joke"],
	"settings": {
		"delicious-decimals": {
			"name": "Delicious Decimals",
			"description": "The amount of (Delicious) Decimals you want to display.\n\n\n[Note: This value will be limited to match your screen size when you open a level]",
			"type": "int",
			"default": 0,
			"min": 0,
			"max": 99999,
			"control": {
				"slider": false
			}
		}
	},
    "links": {
        "source": "https://github.com/GlowRock03/delicious-decimals",
        "community": "https://discord.gg/4GQGcdZhff"
    },
	"dependencies": {
		"geode.node-ids": ">=v1.20.0"
	}
}
